setup.py
nyan_logger/__init__.py
nyan_logger/nyan.py
nyan_logger.egg-info/PKG-INFO
nyan_logger.egg-info/SOURCES.txt
nyan_logger.egg-info/dependency_links.txt
nyan_logger.egg-info/not-zip-safe
nyan_logger.egg-info/top_level.txt