Metadata-Version: 1.0
Name: nyan-logger
Version: 0.1
Summary: A nyan cat log formatter for the python logging module.
Home-page: https://github.com/tomhennigan/nyan_logger
Author: Tom Hennigan, Louise Deason
Author-email: tomhennigan@gmail.com
License: FU
Platform: UNKNOWN
